[{"title":"Hello World","slug":"hello-world","date":"2021-11-04","updated":"2020-11-21","path":"api/posts/16107.json","excerpt":null,"cover":null,"url":"/posts/16107/","abbrlink":16107,"categories":[],"tags":[]},{"title":"取余符号","slug":"取余符号","date":"2021-03-18","updated":"2021-03-18","path":"api/posts/38499.json","excerpt":null,"cover":null,"url":"/posts/38499/","abbrlink":38499,"categories":[{"name":"C++","path":"api/categories/C++.json","url":"/categories/C/"}],"tags":[{"name":"算法","path":"api/tags/算法.json","url":"/tags/算法/"}]},{"title":"Hexo 主题 Mustom 使用指南（对应主题 1.0 版）","slug":"Hexo主题Mustom使用指南（对应主题1-0版）","date":"2020-11-22","updated":"2020-11-22","path":"api/posts/55821.json","excerpt":"<ul><li>本主题 <a href=\"//github.com/jinyaoMa/hexo-theme-mustom\">Mustom</a> 是我参考了卡片式和窗口展示的样式设计的 Hexo 主题。</li><li>本主题通过大量的 replaceWith 函数和 PJAX 来加载，而且用了 Live2D 的插件，初始加载时回流特别厉害。</li><li>本主题可以衍生一个 CSS 的框架，但是作者本人目前还是在给每个组件都弄一个单独的样式表。</li><li>本主题把各类资源文件都分门别类了，在以后添加内容方面应该还是较方便的。</li></ul>","cover":null,"url":"/posts/55821/","abbrlink":55821,"categories":[{"name":"Hexo","path":"api/categories/Hexo.json","url":"/categories/Hexo/"}],"tags":[{"name":"Mustom","path":"api/tags/Mustom.json","url":"/tags/Mustom/"}]},{"title":"12","slug":"1","date":"2020-11-21","updated":"2020-11-22","path":"api/posts/54465.json","excerpt":null,"cover":null,"url":"/posts/54465/","abbrlink":54465,"categories":[{"name":"Linux","path":"api/categories/Linux.json","url":"/categories/Linux/"}],"tags":[{"name":"基础知识","path":"api/tags/基础知识.json","url":"/tags/基础知识/"}]}]